langchain_tests/__init__.py
langchain_tests/base.py
langchain_tests/conftest.py
langchain_tests/py.typed
langchain_tests/integration_tests/__init__.py
langchain_tests/integration_tests/base_store.py
langchain_tests/integration_tests/cache.py
langchain_tests/integration_tests/chat_models.py
langchain_tests/integration_tests/embeddings.py
langchain_tests/integration_tests/indexer.py
langchain_tests/integration_tests/retrievers.py
langchain_tests/integration_tests/tools.py
langchain_tests/integration_tests/vectorstores.py
langchain_tests/unit_tests/__init__.py
langchain_tests/unit_tests/chat_models.py
langchain_tests/unit_tests/embeddings.py
langchain_tests/unit_tests/tools.py
langchain_tests/utils/__init__.py
langchain_tests/utils/pydantic.py
langchain_tests-1.1.2.dist-info/METADATA
langchain_tests-1.1.2.dist-info/WHEEL
langchain_tests-1.1.2.dist-info/RECORD
