Metadata-Version: 2.4
Name: langchain-tests
Version: 1.1.2
Summary: Standard tests for LangChain implementations
Project-URL: Homepage, https://docs.langchain.com/
Project-URL: Documentation, https://docs.langchain.com/
Project-URL: Source, https://github.com/langchain-ai/langchain/tree/master/libs/standard-tests
Project-URL: Changelog, https://github.com/langchain-ai/langchain/releases?q=%22langchain-tests%3D%3D1%22
Project-URL: Twitter, https://x.com/LangChainAI
Project-URL: Slack, https://www.langchain.com/join-community
Project-URL: Reddit, https://www.reddit.com/r/LangChain/
License: MIT
Requires-Python: <4.0.0,>=3.10.0
Requires-Dist: httpx<1.0.0,>=0.28.1
Requires-Dist: langchain-core<2.0.0,>=1.2.2
Requires-Dist: numpy>=1.26.2; python_version < '3.13'
Requires-Dist: numpy>=2.1.0; python_version >= '3.13'
Requires-Dist: pytest-asyncio<2.0.0,>=0.20.0
Requires-Dist: pytest-benchmark
Requires-Dist: pytest-codspeed
Requires-Dist: pytest-recording
Requires-Dist: pytest-socket<1.0.0,>=0.7.0
Requires-Dist: pytest<9.0.0,>=7.0.0
Requires-Dist: syrupy<5.0.0,>=4.0.0
Requires-Dist: vcrpy<8.0.0,>=7.0.0
